Metadata-Version: 2.2
Name: yalkvmom
Version: 0.0.1
Summary: My Package
Author: Alex
Dynamic: author
Dynamic: summary
